COUNTERS/DECADE  COUNTER/decade_counter.v
`timescale 1ns / 1ps

module decade_counter #(parameter N = 4)(
    output reg [N-1:0]q,
    input clk,rst
    );
    always @(posedge clk) begin
    if(rst) begin
    q <= 4'b0000;
    end
    else if(q == 4'b1001) begin
            q <= 4'b0000;
    end
     else begin
          q <= q + 1;
      end
    end
endmodule

COUNTERS/DECADE  COUNTER/decade_counter_tb.v
`timescale 1ns / 1ps

module decade_counter_tb;
    wire [3:0]q;
    reg clk,rst;
    decade_counter #(.N(4)) dut(q,clk,rst);
    
    initial begin
        rst = 1;
        clk = 0;
        #20 rst = 0;
        #500 $finish();
    end
    always #10 clk = ~clk;
    initial begin
      $dumpfile("dump.vcd");
      $dumpvars(0);
    end
endmodule

COUNTERS/DECADE  COUNTER/dump.vcd
$date
	Sun Mar 10 22:09:12 2024
$end
$version
	Icarus Verilog
$end
$timescale
	1ps
$end
$scope module decade_counter_tb $end
$var wire 4 ! q [3:0] $end
$var reg 1 " clk $end
$var reg 1 # rst $end
$scope module dut $end
$var wire 1 " clk $end
$var wire 1 # rst $end
$var parameter 32 $ N $end
$var reg 4 % q [3:0] $end
$upscope $end
$upscope $end
$enddefinitions $end
$comment Show the parameter values. $end
$dumpall
b100 $
$end
#0
$dumpvars
bx %
1#
0"
bx !
$end
#10000
b0 !
b0 %
1"
#20000
0"
0#
#30000
b1 !
b1 %
1"
#40000
0"
#50000
b10 !
b10 %
1"
#60000
0"
#70000
b11 !
b11 %
1"
#80000
0"
#90000
b100 !
b100 %
1"
#100000
0"
#110000
b101 !
b101 %
1"
#120000
0"
#130000
b110 !
b110 %
1"
#140000
0"
#150000
b111 !
b111 %
1"
#160000
0"
#170000
b1000 !
b1000 %
1"
#180000
0"
#190000
b1001 !
b1001 %
1"
#200000
0"
#210000
b0 !
b0 %
1"
#220000
0"
#230000
b1 !
b1 %
1"
#240000
0"
#250000
b10 !
b10 %
1"
#260000
0"
#270000
b11 !
b11 %
1"
#280000
0"
#290000
b100 !
b100 %
1"
#300000
0"
#310000
b101 !
b101 %
1"
#320000
0"
#330000
b110 !
b110 %
1"
#340000
0"
#350000
b111 !
b111 %
1"
#360000
0"
#370000
b1000 !
b1000 %
1"
#380000
0"
#390000
b1001 !
b1001 %
1"
#400000
0"
#410000
b0 !
b0 %
1"
#420000
0"
#430000
b1 !
b1 %
1"
#440000
0"
#450000
b10 !
b10 %
1"
#460000
0"
#470000
b11 !
b11 %
1"
#480000
0"
#490000
b100 !
b100 %
1"
#500000
0"
#510000
b101 !
b101 %
1"
