64 bit register/register_64bit.v
// Code your design here
//Design a 64 bit register with asynchronous,active low reset. Also write its testbench.
module register_64bit(input wire [64-1:0] data_in,
input wire clk,
input wire reset,
output reg [64-1:0] data_out);


always@(posedge clk or negedge reset)begin 

if(reset==0)begin   // active low reset  (!reset)
data_out <= 64'b0;
end
else begin
data_out <= data_in;
end

end


endmodule

64 bit register/register_64bit_tb.sv
// Code your testbench here
// or browse Examples
module register_64bit_tb();
logic [64-1:0] data_in;
logic reset;
bit clk;  // default=0
logic [64-1:0] data_out;

// Instantiate 

//register_64bit dut(data_in,clk,reset,data_out);// methode 1 sequenc matter
//register_64bit dut(.*); //methode 2  test bench variable name same as dut module name
register_64bit dut(.data_out(data_out),.data_in(data_in),.clk(clk),.reset(reset)); 
//methode 3  best practice   sequenc and same name dosent matter



// Clock generation
initial begin
  forever #5 clk = ~clk; // Toggle clock every 5 time units
end

// Initial values
initial begin
  reset = 0;
  data_in = 64'd9; 
  #10; 
  reset = 1; 
  #10; 
  data_in = 64'd1; 
  #10;
  data_in = 64'd2; 
  #10; 
  reset = 0; 
  #10; 
  data_in = 64'd3; 
  #10; 
  data_in = 64'd4; 
  #10;
  data_in = 64'd5; 
  #10; 

  $finish; // End simulation
end

 initial begin 
  
  $dumpfile("dumped.vcd");
  $dumpvars(0);
  #100;
  $finish();
  
 end    
endmodule

64 bit register/dumped.vcd
$date
	Sat Apr 20 01:59:12 2024
$end
$version
	ModelSim Version 10.5b
$end
$timescale
	1ps
$end

$scope module register_64bit_tb $end
$var reg 64 ! data_in [63:0] $end
$var reg 1 " reset $end
$var reg 1 # clk $end
$var wire 1 $ data_out [63] $end
$var wire 1 % data_out [62] $end
$var wire 1 & data_out [61] $end
$var wire 1 ' data_out [60] $end
$var wire 1 ( data_out [59] $end
$var wire 1 ) data_out [58] $end
$var wire 1 * data_out [57] $end
$var wire 1 + data_out [56] $end
$var wire 1 , data_out [55] $end
$var wire 1 - data_out [54] $end
$var wire 1 . data_out [53] $end
$var wire 1 / data_out [52] $end
$var wire 1 0 data_out [51] $end
$var wire 1 1 data_out [50] $end
$var wire 1 2 data_out [49] $end
$var wire 1 3 data_out [48] $end
$var wire 1 4 data_out [47] $end
$var wire 1 5 data_out [46] $end
$var wire 1 6 data_out [45] $end
$var wire 1 7 data_out [44] $end
$var wire 1 8 data_out [43] $end
$var wire 1 9 data_out [42] $end
$var wire 1 : data_out [41] $end
$var wire 1 ; data_out [40] $end
$var wire 1 < data_out [39] $end
$var wire 1 = data_out [38] $end
$var wire 1 > data_out [37] $end
$var wire 1 ? data_out [36] $end
$var wire 1 @ data_out [35] $end
$var wire 1 A data_out [34] $end
$var wire 1 B data_out [33] $end
$var wire 1 C data_out [32] $end
$var wire 1 D data_out [31] $end
$var wire 1 E data_out [30] $end
$var wire 1 F data_out [29] $end
$var wire 1 G data_out [28] $end
$var wire 1 H data_out [27] $end
$var wire 1 I data_out [26] $end
$var wire 1 J data_out [25] $end
$var wire 1 K data_out [24] $end
$var wire 1 L data_out [23] $end
$var wire 1 M data_out [22] $end
$var wire 1 N data_out [21] $end
$var wire 1 O data_out [20] $end
$var wire 1 P data_out [19] $end
$var wire 1 Q data_out [18] $end
$var wire 1 R data_out [17] $end
$var wire 1 S data_out [16] $end
$var wire 1 T data_out [15] $end
$var wire 1 U data_out [14] $end
$var wire 1 V data_out [13] $end
$var wire 1 W data_out [12] $end
$var wire 1 X data_out [11] $end
$var wire 1 Y data_out [10] $end
$var wire 1 Z data_out [9] $end
$var wire 1 [ data_out [8] $end
$var wire 1 \ data_out [7] $end
$var wire 1 ] data_out [6] $end
$var wire 1 ^ data_out [5] $end
$var wire 1 _ data_out [4] $end
$var wire 1 ` data_out [3] $end
$var wire 1 a data_out [2] $end
$var wire 1 b data_out [1] $end
$var wire 1 c data_out [0] $end

$scope module dut $end
$var wire 1 d data_in [63] $end
$var wire 1 e data_in [62] $end
$var wire 1 f data_in [61] $end
$var wire 1 g data_in [60] $end
$var wire 1 h data_in [59] $end
$var wire 1 i data_in [58] $end
$var wire 1 j data_in [57] $end
$var wire 1 k data_in [56] $end
$var wire 1 l data_in [55] $end
$var wire 1 m data_in [54] $end
$var wire 1 n data_in [53] $end
$var wire 1 o data_in [52] $end
$var wire 1 p data_in [51] $end
$var wire 1 q data_in [50] $end
$var wire 1 r data_in [49] $end
$var wire 1 s data_in [48] $end
$var wire 1 t data_in [47] $end
$var wire 1 u data_in [46] $end
$var wire 1 v data_in [45] $end
$var wire 1 w data_in [44] $end
$var wire 1 x data_in [43] $end
$var wire 1 y data_in [42] $end
$var wire 1 z data_in [41] $end
$var wire 1 { data_in [40] $end
$var wire 1 | data_in [39] $end
$var wire 1 } data_in [38] $end
$var wire 1 ~ data_in [37] $end
$var wire 1 !! data_in [36] $end
$var wire 1 "! data_in [35] $end
$var wire 1 #! data_in [34] $end
$var wire 1 $! data_in [33] $end
$var wire 1 %! data_in [32] $end
$var wire 1 &! data_in [31] $end
$var wire 1 '! data_in [30] $end
$var wire 1 (! data_in [29] $end
$var wire 1 )! data_in [28] $end
$var wire 1 *! data_in [27] $end
$var wire 1 +! data_in [26] $end
$var wire 1 ,! data_in [25] $end
$var wire 1 -! data_in [24] $end
$var wire 1 .! data_in [23] $end
$var wire 1 /! data_in [22] $end
$var wire 1 0! data_in [21] $end
$var wire 1 1! data_in [20] $end
$var wire 1 2! data_in [19] $end
$var wire 1 3! data_in [18] $end
$var wire 1 4! data_in [17] $end
$var wire 1 5! data_in [16] $end
$var wire 1 6! data_in [15] $end
$var wire 1 7! data_in [14] $end
$var wire 1 8! data_in [13] $end
$var wire 1 9! data_in [12] $end
$var wire 1 :! data_in [11] $end
$var wire 1 ;! data_in [10] $end
$var wire 1 <! data_in [9] $end
$var wire 1 =! data_in [8] $end
$var wire 1 >! data_in [7] $end
$var wire 1 ?! data_in [6] $end
$var wire 1 @! data_in [5] $end
$var wire 1 A! data_in [4] $end
$var wire 1 B! data_in [3] $end
$var wire 1 C! data_in [2] $end
$var wire 1 D! data_in [1] $end
$var wire 1 E! data_in [0] $end
$var wire 1 F! clk $end
$var wire 1 G! reset $end
$var reg 64 H! data_out [63:0] $end
$upscope $end
$upscope $end
$enddefinitions $end
#0
$dumpvars
b1001 !
0"
0#
b0 H!
0c
0b
0a
0`
0_
0^
0]
0\
0[
0Z
0Y
0X
0W
0V
0U
0T
0S
0R
0Q
0P
0O
0N
0M
0L
0K
0J
0I
0H
0G
0F
0E
0D
0C
0B
0A
0@
0?
0>
0=
0<
0;
0:
09
08
07
06
05
04
03
02
01
00
0/
0.
0-
0,
0+
0*
0)
0(
0'
0&
0%
0$
1E!
0D!
0C!
1B!
0A!
0@!
0?!
0>!
0=!
0<!
0;!
0:!
09!
08!
07!
06!
05!
04!
03!
02!
01!
00!
0/!
0.!
0-!
0,!
0+!
0*!
0)!
0(!
0'!
0&!
0%!
0$!
0#!
0"!
0!!
0~
0}
0|
0{
0z
0y
0x
0w
0v
0u
0t
0s
0r
0q
0p
0o
0n
0m
0l
0k
0j
0i
0h
0g
0f
0e
0d
0F!
0G!
$end
#5
1#
1F!
#10
1"
0#
1G!
0F!
#15
1#
1F!
b1001 H!
1c
1`
#20
b1 !
0#
0B!
0F!
#25
1#
1F!
b1 H!
0`
#30
b10 !
0#
0E!
1D!
0F!
#35
1#
1F!
b10 H!
0c
1b
#40
0"
0#
0G!
0F!
b0 H!
0b
#45
1#
1F!
#50
b11 !
0#
1E!
0F!
#55
1#
1F!
#60
b100 !
0#
0E!
0D!
1C!
0F!
#65
1#
1F!
#70
b101 !
0#
1E!
0F!
